abow/__init__.py
abow/alerts.py
abow/app.py
abow/backend.py
abow/config.py
abow/l10n.py
abow/mdx_tables.py
abow/mdx_wikilinks.py
abow/render.py
abow/tags.py
abow/locale/abow.pot
abow/locale/en/LC_MESSAGES/abow.mo
abow/locale/fr/LC_MESSAGES/abow.mo
abow/static/css/abow.css
abow/static/css/bootstrap.min.css
abow/static/css/highlight.css
abow/static/img/abow.svg
abow/static/img/abow_16.png
abow/static/img/abow_32.png
abow/static/js/abow.js
abow/static/js/autosize.min.js
abow/static/js/bootstrap.bundle.min.js
abow/views/about.tpl
abow/views/edit.tpl
abow/views/error.tpl
abow/views/index.tpl
abow/views/index_nav_item.tpl
abow/views/list_pages.tpl
abow/views/view.tpl
abow-0.5.3.dist-info/METADATA
abow-0.5.3.dist-info/WHEEL
abow-0.5.3.dist-info/licenses/LICENSE.md
abow-0.5.3.dist-info/RECORD
