Metadata-Version: 2.3
Name: abow
Version: 0.5.3
Summary: A Bottle of Wiki — personal wiki
Project-URL: Homepage, https://pypi.org/project/abow/
Author-email: Benoît Monin <benoit.monin@gmx.fr>
License: AGPL-3.0-or-later
License-File: LICENSE.md
Keywords: bottle,markdown,wiki
Classifier: Development Status :: 5 - Production/Stable
Classifier: Framework :: Bottle
Classifier: Intended Audience :: End Users/Desktop
Classifier: License :: OSI Approved :: GNU Affero General Public License v3 or later (AGPLv3+)
Classifier: Operating System :: POSIX
Classifier: Programming Language :: Python :: 3 :: Only
Classifier: Programming Language :: Python :: 3.9
Classifier: Programming Language :: Python :: 3.10
Classifier: Programming Language :: Python :: 3.11
Classifier: Programming Language :: Python :: 3.12
Classifier: Programming Language :: Python :: 3.13
Classifier: Topic :: Internet :: WWW/HTTP :: Dynamic Content :: Wiki
Classifier: Topic :: Internet :: WWW/HTTP :: WSGI :: Application
Requires-Python: >=3.9
Requires-Dist: bottle>=0.12.0
Requires-Dist: markdown>=3.2
Requires-Dist: pymdown-extensions>=7.0
Provides-Extra: dev
Requires-Dist: build; extra == 'dev'
Requires-Dist: coverage; extra == 'dev'
Requires-Dist: flake8; extra == 'dev'
Requires-Dist: pytest; extra == 'dev'
Requires-Dist: tox; extra == 'dev'
Provides-Extra: extra
Requires-Dist: pygments>=2.4; extra == 'extra'
